LICENSE
MANIFEST.in
README.md
setup.cfg
setup.py
balu/__init__.py
balu.egg-info/PKG-INFO
balu.egg-info/SOURCES.txt
balu.egg-info/dependency_links.txt
balu.egg-info/requires.txt
balu.egg-info/top_level.txt
balu/Classification/Bcl_construct.py
balu/Classification/Bcl_dmin.py
balu/Classification/Bcl_knn.py
balu/Classification/Bcl_lda.py
balu/Classification/Bcl_maha.py
balu/Classification/Bcl_nn.py
balu/Classification/Bcl_outscore.py
balu/Classification/Bcl_qda.py
balu/Classification/Bcl_structure.py
balu/Classification/Bcl_svm.py
balu/Classification/__init__.py
balu/DataSelectionAndGeneration/Bds_gaussgen.py
balu/DataSelectionAndGeneration/Bds_nostratify.py
balu/DataSelectionAndGeneration/__init__.py
balu/FeatureAnalysis/Bfa_jfisher.py
balu/FeatureAnalysis/Bfa_mRMR.py
balu/FeatureAnalysis/Bfa_mutualinfo.py
balu/FeatureAnalysis/Bfa_relevance.py
balu/FeatureAnalysis/Bfa_score.py
balu/FeatureAnalysis/Bfa_sp100.py
balu/FeatureAnalysis/__init__.py
balu/FeatureExtraction/Bfx_all.py
balu/FeatureExtraction/Bfx_basicgeo.py
balu/FeatureExtraction/Bfx_basicint.py
balu/FeatureExtraction/Bfx_fitellipse.py
balu/FeatureExtraction/Bfx_flusser.py
balu/FeatureExtraction/Bfx_fourier.py
balu/FeatureExtraction/Bfx_fourierdes.py
balu/FeatureExtraction/Bfx_geo.py
balu/FeatureExtraction/Bfx_haralick.py
balu/FeatureExtraction/Bfx_hugeo.py
balu/FeatureExtraction/Bfx_lbp.py
balu/FeatureExtraction/__init__.py
balu/FeatureSelection/Bfs_clean.py
balu/FeatureSelection/Bfs_noposition.py
balu/FeatureSelection/Bfs_sfs.py
balu/FeatureSelection/__init__.py
balu/FeatureTransformation/Bft_norm.py
balu/FeatureTransformation/Bft_pca.py
balu/FeatureTransformation/Bft_sigmoid.py
balu/FeatureTransformation/__init__.py
balu/ImageProcessing/Bim_d1.py
balu/ImageProcessing/Bim_d2.py
balu/ImageProcessing/Bim_inthist.py
balu/ImageProcessing/Bim_inthistread.py
balu/ImageProcessing/Bim_maxmin.py
balu/ImageProcessing/Bim_morphoreg.py
balu/ImageProcessing/Bim_rgb2hcm.py
balu/ImageProcessing/Bim_segbalu.py
balu/ImageProcessing/Bim_segmowgli.py
balu/ImageProcessing/Bim_segotsu.py
balu/ImageProcessing/__init__.py
balu/ImagesAndData/Balu.jpg
