Metadata-Version: 1.1
Name: balu
Version: 0.1.18
Summary: Python implementation of Balu Toolbox by Domingo Mery (http://dmery.ing.puc.cl/index.php/balu/)
Home-page: https://github.com/dipaco/balu-python
Author: Diego Patiño
Author-email: dapatinoco@unal.edu.com
License: UNKNOWN
Download-URL: https://github.com/dipaco/balu-python/releases/tag/0.1.18
Keywords: Computer Vision,Machine Learning,Image Processing
Platform: UNKNOWN
